Metadata-Version: 1.0
Name: hello-pypis
Version: 1.2.3
Summary: a minimal example package (pure python version)
Home-page: UNKNOWN
Author: The scikit-build team
Author-email: UNKNOWN
License: MIT
Platform: UNKNOWN
